{
	"opcode":		"a",
	"description":	"",
	"parameters":	[
		{
			"name": "Channel",
			"type": "String",
			"description":	""
		},
		{
			"name": "Nickname",
			"type": "String",
			"description":	""
		},
		{
			"name": "ScrollSpeed",
			"type": "Integer",
			"description":	""
		},
		{
			"name": "Width",
			"type": "Integer",
			"description":	""
		},
		{
			"name": "Height",
			"type": "Integer",
			"description":	""
		},
		{
			"name": "PositionX",
			"type": "Integer",
			"description":	""
		},
		{
			"name": "PositionY",
			"type": "Integer",
			"description":	""
		},
		{
			"name": "BackgroundImageURL",
			"type": "String",
			"description":	""
		},
		{
			"name": "BackgroundImagePosition",
			"type": "Integer",
			"description":	""
		},
		{
			"name": "Unknown",
			"type": "String",
			"description":	""
		},
		{
			"name": "ForegroundColor",
			"type": "String",
			"description":	""
		},
		{
			"name": "BackgroundColor",
			"type": "String",
			"description":	""
		},
		{
			"name": "RedColor",
			"type": "String",
			"description":	""
		},
		{
			"name": "BlueColor",
			"type": "String",
			"description":	""
		},
		{
			"name": "FontSize",
			"type": "Integer",
			"description":	""
		},
		{
			"name": "LineSpace",
			"type": "Integer",
			"description":	""
		},
		{
			"name": "UserlistFontSize",
			"type": "Integer",
			"description":	""
		},
		{
			"name": "UserlistBackgroundColor",
			"type": "Integer",
			"description":	""
		},
		{
			"name": "ComboBox",
			"type": "Boolean",
			"description":	""
		},
		{
			"name": "ComboBox Value",
			"type": "String",
			"description":	""
		},
		{
			"name": "Unknown1",
			"type": "Boolean",
			"description":	""
		},
		{
			"name": "MaxMessageLength",
			"type": "Integer",
			"description":	""
		},
		{
			"name": "ButtonHelp",
			"type": "Boolean",
			"description":	""
		},
		{
			"name": "ButtonReport",
			"type": "Boolean",
			"description":	""
		},
		{
			"name": "ButtonFeedback",
			"type": "Boolean",
			"description":	""
		},
		{
			"name": "ButtonMessages",
			"type": "Boolean:Integer",
			"description":	""
		},
		{
			"name": "Unknown2",
			"type": "String",
			"description":	""
		},
		{
			"name": "TemporaryPassword",
			"type": "String",
			"description":	""
		},
		{
			"name": "Unknown3",
			"type": "Boolean",
			"description":	""
		},
		{
			"name": "Unknown4",
			"type": "Boolean",
			"description":	""
		}
	]
}